src/__init__.py
src/clarac_utils.py
src/cli.py
src/constants.py
src/container.py
src/main.py
src/pipeline_utils.py
src/topology_sort.py
src/triton_utils.py
src/utils.py
tests/__init__.py
tests/test_clarac_utils.py
tests/test_cli.py
tests/test_container.py
tests/test_main.py
tests/test_pipeline_utils.py
tests/test_topology_sort.py
tests/test_triton_utils.py
tests/test_utils.py
nvidia_clara_cpost-0.8.1.dist-info/LICENSE
nvidia_clara_cpost-0.8.1.dist-info/METADATA
nvidia_clara_cpost-0.8.1.dist-info/WHEEL
nvidia_clara_cpost-0.8.1.dist-info/entry_points.txt
nvidia_clara_cpost-0.8.1.dist-info/top_level.txt
nvidia_clara_cpost-0.8.1.dist-info/RECORD
