Metadata-Version: 2.1
Name: nvidia-clara-cpost
Version: 0.8.1
Summary: Python package to run Clara Pipeline Operator Sizing Tool (cpost)
Home-page: https://gitlab-master.nvidia.com/Clara/sdk/-/tree/main/Tools/cpost
Author: NVIDIA Clara Deploy
License: UNKNOWN
Platform: UNKNOWN
Classifier: Programming Language :: Python :: 3
Classifier: Operating System :: OS Independent
Requires-Python: >=3.8
Requires-Dist: psutil (==5.8.0)
Requires-Dist: pytest (==6.2.4)
Requires-Dist: PyYAML (==5.4.1)
Requires-Dist: requests (==2.25.1)
Requires-Dist: tabulate (==0.8.9)
